umf/__init__.py
umf/constants/__init__.py
umf/constants/dimensions.py
umf/constants/exceptions.py
umf/core/__init__.py
umf/core/create.py
umf/functions/__init__.py
umf/functions/distributions/TODO.md
umf/functions/distributions/__init__.py
umf/functions/distributions/continuous_2pi_interval.py
umf/functions/distributions/continuous_bounded_interval.py
umf/functions/distributions/continuous_semi_infinite_interval.py
umf/functions/distributions/continuous_variable_support.py
umf/functions/distributions/continuous_whole_line_support.py
umf/functions/distributions/discrete_finite_support.py
umf/functions/distributions/discrete_infinite_support.py
umf/functions/distributions/mixed_discrete_continuous.py
umf/functions/optimization/__init__.py
umf/functions/optimization/bowl_shaped.py
umf/functions/optimization/drops_steps.py
umf/functions/optimization/many_local_minima.py
umf/functions/optimization/plate_shaped.py
umf/functions/optimization/special.py
umf/functions/optimization/valley_shaped.py
umf/functions/other/__init__.py
umf/functions/other/support_functions.py
umf/functions/other/test/__init__.py
umf/functions/other/test/test_support_functios.py
umf/images/__init__.py
umf/images/diagrams.py
umf/meta/__init__.py
umf/meta/api.py
umf/meta/functions.py
umf/meta/plots.py
umf/types/__init__.py
umf/types/static_types.py
useful_math_functions_functions-0.1.0.dist-info/LICENSE.md
useful_math_functions_functions-0.1.0.dist-info/METADATA
useful_math_functions_functions-0.1.0.dist-info/WHEEL
useful_math_functions_functions-0.1.0.dist-info/RECORD
