Metadata-Version: 2.1
Name: useful-math-functions-functions
Version: 0.1.0
Summary: useful-math-functions for Optimization, Benchmarking, Visualizing, and more ...
Author: Anselm Hahn
Author-email: anselm.hahn@gmail.com
Requires-Python: >=3.10,<3.12
Classifier: Programming Language :: Python :: 3
Classifier: Programming Language :: Python :: 3.10
Classifier: Programming Language :: Python :: 3.11
Provides-Extra: all
Provides-Extra: matplotlib
Provides-Extra: plotly
Requires-Dist: kaleido (==0.2.1) ; extra == "plotly" or extra == "all"
Requires-Dist: matplotlib (>=3.7.2,<4.0.0) ; extra == "matplotlib" or extra == "all"
Requires-Dist: numpy (>=1.23.5,<2.0.0)
Requires-Dist: plotly (>=5.16.0,<6.0.0) ; extra == "plotly" or extra == "all"
Requires-Dist: pydantic (>=2.0.0,<3.0.0)
Requires-Dist: scipy (>=1.11.2,<2.0.0)
